cookie_notification/__init__.py
cookie_notification/apps.py
cookie_notification/const.py
cookie_notification/context_processors.py
cookie_notification/controllers.py
cookie_notification/models.py
cookie_notification/utils.py
cookie_notification/domain/__init__.py
cookie_notification/domain/const.py
cookie_notification/migrations/0001_initial.py
cookie_notification/migrations/0002_text_to_char_field.py
cookie_notification/migrations/0003_auto_20260121_1501.py
cookie_notification/migrations/__init__.py
cookie_notification/web/__init__.py
cookie_notification/web/packs.py
cookie_notification/web/ui.py
cookie_notification/web/templates/ui-js/cookie-notification.js
cookie_notification-0.3.4.dist-info/METADATA
cookie_notification-0.3.4.dist-info/WHEEL
cookie_notification-0.3.4.dist-info/top_level.txt
cookie_notification-0.3.4.dist-info/RECORD
